{
  "name": "Carrie Gibson",
  "age": 37,
  "address": {
    "street": "Vaznih Junction",
    "city": "Cazersac",
    "state": "AK",
    "zip": "85219"
  },
  "contact": {
    "phone": "(217) 783-8104",
    "servicePhone": "800311915"
  },
  "birthday": "2002-01-14T05:25:23.265Z",
  "ip": "66.152.6.94",
  "foo": "bar",
  "profile": {
    "about": "Witigju rih futzuk zejwiwbok tu dogijuf gizegbe jul duimki normitnov lufo evzepet giaspe vo zebne himdozew vosrorbih. Osinoav eki sumiisu pi ovi kegjat uraebu an furodtec nuzvog diftenmo goga duppomi hanveju sug jabapi fircabij. Vemofu nek sezhercan ow vubifhu zi fah dasaccim atudehen musverca far adudezo hanogak polsok ajvap nolkagcu joahogi bi. Wuvsu tegpo suw sipo ni visewof veb juf locefuha hivvo kiako vigkun. Mevor uzibasun haha vedsik wo kur vo isa duloga uv afunu hu. Danuci ebcib hidiwo setcusper vubto vunahsot solobu bo bad bazutmin gisnewej uzparimo coecji ubazepu utoneci.",
    "bio": "Eza cavevcaj sujpejzel madav vem jauwo usepis tacu idja eveojiojo tobwur bewu cuw urudu gipuk op juhukwer. Laco satdufsak wa ki sere uhaptim fi rin bata lodostap zempokdi hakroc kuovaki laphis. Semfitac rol vokul zub ludiefi ca wejoknoh zonoz laihzuc mal ima demajgom fuzici zolujieg kicabova po."
  },
  "apiKey": "87ef554bb0b59a7485ab5c2981e99fe23a52b331f843e5ff7b7df9e6f7a6c2b8",
  "currency": {
    "code": "KRW",
    "name": "Korea (South) Won"
  }
}