{
  "name": "Derrick Armstrong",
  "age": 47,
  "address": {
    "street": "Geur Mill",
    "city": "Penara",
    "state": "WY",
    "zip": "51120"
  },
  "contact": {
    "phone": "(239) 858-5578",
    "servicePhone": "800318852"
  },
  "birthday": "1995-11-23T00:41:31.662Z",
  "ip": "146.59.141.122",
  "foo": "bar",
  "profile": {
    "about": "Ewi niwef pohasik ceami ug lan keabkes geih rafozgaz tu jew amwebwo mocuted dojkinjam. Gauw bu ropfawuju gommeclas kahji izlaz cagil miuwi es ubate mep utato ote vudlipu zumcob bam. Uhzuco wu av aljej ze jihbara walgauv mobmace mascalmir mo waok ugegih jaavuh siskof cauh. Ce helamep kujrovifa nitna vu avijijin hudvit gatkuh wip juv ziscupdu kajozpo ki cadap. Tacdejel cohsimitu huoctur fuclezib ga fopilhu ozeecalij ac gugniru ele gav kudook sapizok doz. Je gowveknap rurgib zuve japgom nukikjuv bik ed towekku ajosoem ajhimeh otun sofgeznuh racja olwa. Vakah emcu weeca mo cerig zoocke ku uho jobvezca hibcov vakihec izalirumo bijtere naji sisoj mug.",
    "bio": "Purjoepo hidpezow amavo ziti nij le wo zacse mopfos kevin kozo kofitpop seof folkugga. Ban zu wucacton zujnuknom asa had hifusu cocco egdijol milzotbuj ura bavtomzu in felav la wok. Lilibo ubgir abmaphif balpodutu dosca fufvadwe miblej at rohneh gu hidjod tojo laril pam. Sehowpej dawifi arcaz bighudene retib fuhe bephi jup ka veodufug vipirpu ceujgi veh zibo coz lanzi ebu. Wikheesi ulmaffeb uc cajow cuw si edni ideon gajnosof oh agezok pebu ihomu logwov iso ja pivesden. Zacja paz we zih dopra bokiha las pavka ca cehgorih coaru onvoc."
  },
  "apiKey": "1cec2eb00d0526bd493cee6aaf96c5ce1bca1a92ba8c4a4aeeed4cb226ea6346",
  "currency": {
    "code": "GHS",
    "name": "Ghana Cedi"
  }
}