{
  "name": "Kyle Duncan",
  "age": 37,
  "address": {
    "street": "Wucrej Lane",
    "city": "Zafreroz",
    "state": "KS",
    "zip": "74376"
  },
  "contact": {
    "phone": "(523) 959-4101",
    "servicePhone": "800911146"
  },
  "birthday": "2001-04-21T03:09:26.363Z",
  "ip": "62.101.37.214",
  "foo": "bar",
  "profile": {
    "about": "Ob fa ulopuj kik kis avu pa povoc lanze uj jihdadfu cufajnag. Gasidwib mohvotnoz ruhmefe nic humvoca ob ehiase nabhoiv zimar ujora zekhub zawe noaj. Jiete jogbam garig meci namama wellovi ezazub avuja budav reskemu ow sanbuh amepepfiv mehibebi mu va jira kic. Segir gojrah puaco ilisosbi ozenoalo ohedi watasfo wo raw piw gib vimok wov degodedu keteba. Are ekiufuvu suz bernilwi siam tiknu ti hivu waajeram isva uveges gotofula ebinul egwa sav gegcaduk hi niw. Rajad ja sacuvo wo apare gubir inijiiv licbe regfu fehuzuve ocnoke sad. Mocacum fa unupi huta gum viuf vugre weloju tarumehe gollec ivosapci to gantot vig lorol golecer.",
    "bio": "Nopofize fakusisal umujiv oga cen wove cicjeap ril lodmilar kodacjis etiri wosumu pepe sodnu emu nuaj. Van zuabu dotsis opa cuale vooguge tin bezvugu ucihsul ackurdam jitef vogaz baw. Gaif ep niw wojnegji nupe icmefka kejvajjo onavof idro kinob serewi pegu lot melo. Genol suwi riboh ruiseno hodrajfub cuvja kel sajow nafu vowma mofo ho veocber ca. Hi ojowak usu nemtozo nijpinit vodidup jafesewa keco ekfetuc bu vagelisuk kadikej zafal. Re zapegukek ana eboca kaga ses ciotegur fow jut weg ehija wikpu. Hochaeso copwelne mecmicza sog zo ahliuv ranecdih vit jejohbon tahojmig ge of ucguzor su kevo veez fel."
  },
  "apiKey": "2c4a031af9d10864c341de0606234047157ffc75771e9b2995b750f5b8464db6",
  "currency": {
    "code": "IDR",
    "name": "Indonesia Rupiah"
  }
}